astropype/__init__.py
astropype/badpixel.py
astropype/database.py
astropype/decorator.py
astropype/fitsreduction.py
astropype/funcs.py
astropype/master.py
astropype/pixelmath.py
astropype/sky.py
astropype/utilities.py
scripts/ref_stars.py
scripts/select_images.py
scripts/set_ell_src_head.py
scripts/write_wcs_to_header.py
astropype-1.0.0.dist-info/LICENSE
astropype-1.0.0.dist-info/METADATA
astropype-1.0.0.dist-info/WHEEL
astropype-1.0.0.dist-info/top_level.txt
astropype-1.0.0.dist-info/RECORD
