Metadata-Version: 2.1
Name: astropype
Version: 1.0.0
Summary: Alternative float type for scientific measurements.
Author-email: Jan-Niklas Pippert <jnpippert@mpe.mpg.de>
Project-URL: Homepage, https://github.com/jnpippert/streamPy
Project-URL: Bug Tracker, https://github.com/jnpippert/streamPy/issues
Classifier: Programming Language :: Python :: 3
Classifier: License :: OSI Approved :: MIT License
Classifier: Operating System :: OS Independent
Requires-Python: >=3.9
License-File: LICENSE
